flask_loopback/__init__.py
flask_loopback/__version__.py
flask_loopback/_compat.py
flask_loopback/dispatch.py
flask_loopback/flask_loopback.py
Flask_Loopback-1.6.0.dist-info/AUTHORS
Flask_Loopback-1.6.0.dist-info/LICENSE
Flask_Loopback-1.6.0.dist-info/METADATA
Flask_Loopback-1.6.0.dist-info/WHEEL
Flask_Loopback-1.6.0.dist-info/pbr.json
Flask_Loopback-1.6.0.dist-info/top_level.txt
Flask_Loopback-1.6.0.dist-info/RECORD
