Metadata-Version: 2.1
Name: Flask-Loopback
Version: 1.6.0
Summary: Library for faking HTTP requests using flask applications without actual network operations
Home-page: https://github.com/vmalloc/flask-loopback
Author: Rotem Yaari
Author-email: vmalloc@gmail.com
License: BSD3
Classifier: Programming Language :: Python :: 3.8
Classifier: Programming Language :: Python :: 3.9
Classifier: Programming Language :: Python :: 3.10
Classifier: Programming Language :: Python :: 3.11
License-File: LICENSE
License-File: AUTHORS
Requires-Dist: requests
Requires-Dist: Flask
Requires-Dist: six
Requires-Dist: URLObject
Requires-Dist: werkzeug >=1.0.0
Requires-Dist: unittest2 ; (python_version<'2.7')
Requires-Dist: contextlib2 ; (python_version<'3.3')
Provides-Extra: testing
Requires-Dist: pytest ; extra == 'testing'
Requires-Dist: astroid ~=1.5.3 ; (python_version == "2.7") and extra == 'testing'
Requires-Dist: pylint ~=1.7.2 ; (python_version == "2.7") and extra == 'testing'
Requires-Dist: astroid >=2.0 ; (python_version >= "3.4") and extra == 'testing'
Requires-Dist: pylint ~=2.3.1 ; (python_version >= "3.4") and extra == 'testing'
